<xml xmlns:o="urn:schemas-microsoft-com:office:office">
 <o:MainFile HRef="../MRT_메리엇다낭(2025).html"/>
 <o:File HRef="2025%20MH%20A군%20신규요금표_vba_386_image001.png"
  PublicationID="2025 MH A군 신규요금표_vba_386"/>
 <o:File HRef="2025%20MH%20A군%20신규요금표_vba_386_image002.png"
  PublicationID="2025 MH A군 신규요금표_vba_386"/>
 <o:File HRef="2025%20MH%20A군%20신규요금표_vba_386_image003.png"
  PublicationID="2025 MH A군 신규요금표_vba_386"/>
 <o:File HRef="2025%20MH%20A군%20신규요금표_vba_386_image004.png"
  PublicationID="2025 MH A군 신규요금표_vba_386"/>
 <o:File HRef="2025%20MH%20A군%20신규요금표_vba_386_image005.png"
  PublicationID="2025 MH A군 신규요금표_vba_386"/>
 <o:File HRef="2025%20MH%20A군%20신규요금표_vba_386_image006.png"
  PublicationID="2025 MH A군 신규요금표_vba_386"/>
 <o:File HRef="2025%20MH%20A군%20신규요금표_vba_386_image007.png"
  PublicationID="2025 MH A군 신규요금표_vba_386"/>
 <o:File HRef="2025%20MH%20A군%20신규요금표_vba_386_image008.png"
  PublicationID="2025 MH A군 신규요금표_vba_386"/>
 <o:File HRef="filelist.xml"/>
</xml>